pyawskit/__init__.py
pyawskit/aws.py
pyawskit/aws_codeartifact_npm_env_config_code.py
pyawskit/aws_codeartifact_pip_env_config_code.py
pyawskit/aws_ecr_login_code.py
pyawskit/common.py
pyawskit/configs.py
pyawskit/devices.py
pyawskit/inet.py
pyawskit/main.py
pyawskit/os_utils.py
pyawskit/roles.py
pyawskit/static.py
pyawskit/utils.py
pyawskit-0.1.87.dist-info/LICENSE
pyawskit-0.1.87.dist-info/METADATA
pyawskit-0.1.87.dist-info/WHEEL
pyawskit-0.1.87.dist-info/entry_points.txt
pyawskit-0.1.87.dist-info/top_level.txt
pyawskit-0.1.87.dist-info/RECORD
