Metadata-Version: 2.1
Name: pyawskit
Version: 0.1.87
Summary: Pyawskit is your AWS Swiss Army Knife
Home-page: https://veltzer.github.io/pyawskit
Download-URL: https://github.com/veltzer/pyawskit
Author: Mark Veltzer
Author-email: mark.veltzer@gmail.com
Maintainer: Mark Veltzer
Maintainer-email: mark.veltzer@gmail.com
License: MIT
Keywords: aws,utils,python,api,command,line
Platform: python3
Classifier: Development Status :: 4 - Beta
Classifier: Environment :: Console
Classifier: Operating System :: OS Independent
Classifier: Programming Language :: Python
Classifier: Programming Language :: Python :: 3
Classifier: Programming Language :: Python :: 3 :: Only
Classifier: Programming Language :: Python :: 3.11
Classifier: Topic :: Utilities
Classifier: License :: OSI Approved :: MIT License
License-File: LICENSE
Requires-Dist: pylogconf
Requires-Dist: pyfakeuse
Requires-Dist: pypipegzip
Requires-Dist: tqdm
Requires-Dist: requests
Requires-Dist: boto3
Requires-Dist: pymount
Requires-Dist: ujson
Requires-Dist: sultan
Requires-Dist: pytconf
Requires-Dist: pyapikey
Requires-Dist: furl
Requires-Dist: docker-py
